qapp_braket/__init__.py
qapp_braket/async_tasks/__init__.py
qapp_braket/async_tasks/braket_circuit_export_task.py
qapp_braket/component/__init__.py
qapp_braket/component/backend/__init__.py
qapp_braket/component/backend/braket_invocation.py
qapp_braket/factory/__init__.py
qapp_braket/factory/braket_device_factory.py
qapp_braket/factory/braket_handler_factory.py
qapp_braket/factory/braket_provider_factory.py
qapp_braket/handler/__init__.py
qapp_braket/handler/invocation_handler.py
qapp_braket/model/__init__.py
qapp_braket/model/device/__init__.py
qapp_braket/model/device/aws_braket_device.py
qapp_braket/model/device/oqc_cloud_device.py
qapp_braket/model/device/qapp_braket_device.py
qapp_braket/model/provider/__init__.py
qapp_braket/model/provider/aws_braket_provider.py
qapp_braket/model/provider/oqc_cloud_provider.py
qapp_braket/model/provider/qapp_braket_provider.py
qapp_braket/util/__init__.py
qapp_braket/util/circuit_convert_utils.py
qapp_braket-0.0.9.dist-info/LICENSE
qapp_braket-0.0.9.dist-info/METADATA
qapp_braket-0.0.9.dist-info/WHEEL
qapp_braket-0.0.9.dist-info/top_level.txt
qapp_braket-0.0.9.dist-info/RECORD
