Metadata-Version: 2.2
Name: qapp-braket
Version: 0.0.9
Summary: QApp braket library supporting QApp Platform for Quantum Computing
Author-email: "CITYNOW Co. Ltd. " <corp@citynow.vn>
License: The MIT License (MIT)
Project-URL: Homepage, https://citynow.asia/
Keywords: qapp,qapp-braket,braket,quantum
Classifier: License :: OSI Approved :: MIT License
Classifier: Programming Language :: Python
Classifier: Programming Language :: Python :: 3
Requires-Python: >=3.7
License-File: LICENSE
Requires-Dist: qapp-common==0.0.10.dev1
Requires-Dist: amazon-braket-sdk==1.83.0
Requires-Dist: oqc-qcaas-client==3.7.0
Requires-Dist: qiskit
Requires-Dist: pytket
Requires-Dist: pytket-braket
Provides-Extra: dev
Requires-Dist: black; extra == "dev"
Requires-Dist: bumpver; extra == "dev"
Requires-Dist: isort; extra == "dev"
Requires-Dist: pip-tools; extra == "dev"
Requires-Dist: pytest; extra == "dev"
